tuneout/__init__.py
tuneout/service.py
tuneout/wsgi.py
tuneout/classes/__init__.py
tuneout/classes/deezer.py
tuneout/classes/youtube_music.py
tuneout/docs/index.html
tuneout/docs/assets/bootstrap/css/bootstrap.min.css
tuneout/docs/assets/bootstrap/js/bootstrap.min.js
tuneout/docs/assets/css/styles.min.css
tuneout/docs/assets/img/16.png
tuneout/docs/assets/img/180.png
tuneout/docs/assets/img/192.png
tuneout/docs/assets/img/32.png
tuneout/docs/assets/img/512.png
tuneout/docs/assets/img/wave_background.svg
tuneout/docs/assets/js/jquery.min.js
tuneout/docs/assets/js/script.min.js
tuneout-0.0.3.dist-info/LICENSE
tuneout-0.0.3.dist-info/METADATA
tuneout-0.0.3.dist-info/WHEEL
tuneout-0.0.3.dist-info/entry_points.txt
tuneout-0.0.3.dist-info/top_level.txt
tuneout-0.0.3.dist-info/RECORD
