Metadata-Version: 2.1
Name: tuneout
Version: 0.0.3
Summary: The Open-Source Music Sharing Tool
Author-email: Kaan Giray Buzluk <kaangiray26@protonmail.com>
License: GNU GENERAL PUBLIC LICENSE
Project-URL: Homepage, https://github.com/kaangiray26/tuneout
Project-URL: Bug Tracker, https://github.com/kaangiray26/tuneout/issues
Classifier: Programming Language :: Python :: 3
Classifier: License :: OSI Approved :: GNU General Public License v3 (GPLv3)
Classifier: Operating System :: OS Independent
Requires-Python: >=3.7
License-File: LICENSE
Requires-Dist: requests
Requires-Dist: Flask
Requires-Dist: ratelimit
Requires-Dist: flask-cors
Requires-Dist: ytmusicapi
